secretmod/__init__.py
secretmod/pytransform.pyd
secretmod/test.py
secretmod-0.0.1.dist-info/METADATA
secretmod-0.0.1.dist-info/WHEEL
secretmod-0.0.1.dist-info/top_level.txt
secretmod-0.0.1.dist-info/RECORD
