Metadata-Version: 2.1
Name: secretmod
Version: 0.0.1
Summary: Support modules for app deployment
Home-page: UNKNOWN
Author: Josh Koh
License: UNKNOWN
Platform: UNKNOWN
Classifier: Programming Language :: Python :: 3
Classifier: License :: OSI Approved :: MIT License
Classifier: Operating System :: OS Independent
Requires-Python: >=3.6
